robofactor/__init__.py
robofactor/analysis.py
robofactor/config.py
robofactor/dspy_modules.py
robofactor/evaluation.py
robofactor/function_extraction.py
robofactor/main.py
robofactor/training_data.json
robofactor/ui.py
robofactor/utils.py
robofactor-0.1.1.dist-info/METADATA
robofactor-0.1.1.dist-info/WHEEL
robofactor-0.1.1.dist-info/entry_points.txt
robofactor-0.1.1.dist-info/licenses/LICENSE
robofactor-0.1.1.dist-info/RECORD
