Metadata-Version: 2.4
Name: Robofactor
Version: 0.1.1
Summary: The robot who refactors: /[^_^]\
Project-URL: Homepage, https://github.com/ethan-wickstrom/robofactor
Project-URL: Repository, https://github.com/ethan-wickstrom/robofactor.git
Project-URL: Issues, https://github.com/ethan-wickstrom/robofactor/issues
Project-URL: Documentation, https://github.com/ethan-wickstrom/robofactor#readme
Author-email: ethan-wickstrom <e.t.wickstrom@wustl.edu>
License-File: LICENSE
Classifier: Development Status :: 3 - Alpha
Classifier: Intended Audience :: Developers
Classifier: Programming Language :: Python :: 3.10
Classifier: Programming Language :: Python :: 3.11
Classifier: Programming Language :: Python :: 3.12
Classifier: Programming Language :: Python :: 3.13
Classifier: Topic :: Software Development :: Code Generators
Classifier: Topic :: Software Development :: Libraries :: Application Frameworks
Requires-Python: >=3.10
Requires-Dist: dspy-ai==2.6.19
Requires-Dist: flake8>=7.2.0
Requires-Dist: mlflow>=3.1.0
Requires-Dist: pyflakes>=3.3.2
Requires-Dist: pyright>=1.1.402
Requires-Dist: returns>=0.25.0
Requires-Dist: rich>=13.7.1
Requires-Dist: toml>=0.10.2
Requires-Dist: typer>=0.16.0
